dexcontrol_rosbridge/__init__.py
dexcontrol_rosbridge/multiprocess_sensor_manager.py
dexcontrol_rosbridge/sensor_configs.py
dexcontrol_rosbridge/worker_processes.py
dexcontrol_rosbridge/zenoh_utils.py
dexcontrol_rosbridge/configs/__init__.py
dexcontrol_rosbridge/configs/config_loader.py
dexcontrol_rosbridge/configs/sensor_mapping.yaml
dexcontrol_rosbridge/converters/__init__.py
dexcontrol_rosbridge/converters/camera_converter.py
dexcontrol_rosbridge/converters/chassis_imu_converter.py
dexcontrol_rosbridge/converters/compressed_camera_converter.py
dexcontrol_rosbridge/converters/head_imu_converter.py
dexcontrol_rosbridge/converters/lidar_converter.py
dexcontrol_rosbridge/converters/wrist_camera_converter.py
dexcontrol_rosbridge/subscribers/__init__.py
dexcontrol_rosbridge/subscribers/base_subscriber.py
dexcontrol_rosbridge/subscribers/camera_subscriber.py
dexcontrol_rosbridge/subscribers/chassis_imu_subscriber.py
dexcontrol_rosbridge/subscribers/head_imu_subscriber.py
dexcontrol_rosbridge/subscribers/lidar_subscriber.py
dexcontrol_rosbridge/subscribers/wrist_camera_subscriber.py
dexcontrol_rosbridge-0.3.0.dist-info/METADATA
dexcontrol_rosbridge-0.3.0.dist-info/WHEEL
dexcontrol_rosbridge-0.3.0.dist-info/licenses/LICENSE
dexcontrol_rosbridge-0.3.0.dist-info/RECORD
