Metadata-Version: 2.4
Name: dexcontrol-rosbridge
Version: 0.3.0
Summary: A Python bridge for ROS2 sensor data republishing with Zenoh communication
Project-URL: Homepage, https://github.com/dexmate-ai/dexcontrol-rosbridge
Project-URL: Repository, https://github.com/dexmate-ai/dexcontrol-rosbridge
Project-URL: Issues, https://github.com/dexmate-ai/dexcontrol-rosbridge/issues
Author-email: Guofei Chen <contact@dexmate.ai>
License: AGPL-3.0
License-File: LICENSE
Keywords: bridge,robotics,ros2,sensors,zenoh
Classifier: Development Status :: 3 - Alpha
Classifier: Intended Audience :: Developers
Classifier: Intended Audience :: Science/Research
Classifier: License :: OSI Approved :: GNU Affero General Public License v3
Classifier: Programming Language :: Python :: 3
Classifier: Programming Language :: Python :: 3.10
Classifier: Programming Language :: Python :: 3.11
Classifier: Programming Language :: Python :: 3.12
Classifier: Topic :: Scientific/Engineering
Requires-Python: >=3.10
Requires-Dist: dexcontrol>=0.3.2
Requires-Dist: eclipse-zenoh>=0.11.0
Requires-Dist: loguru>=0.7.0
Requires-Dist: numpy>=1.24.0
Requires-Dist: tyro
